QtKuaisuRumenXilieJiaocheng/README.md
QtKuaisuRumenXilieJiaocheng/__init__.py
QtKuaisuRumenXilieJiaocheng/__main__.py
QtKuaisuRumenXilieJiaocheng/file.epub
QtKuaisuRumenXilieJiaocheng/index.html
QtKuaisuRumenXilieJiaocheng/css/__init__.py
QtKuaisuRumenXilieJiaocheng/css/annotations.css
QtKuaisuRumenXilieJiaocheng/css/main.css
QtKuaisuRumenXilieJiaocheng/css/normalize.css
QtKuaisuRumenXilieJiaocheng/css/popup.css
QtKuaisuRumenXilieJiaocheng/font/__init__.py
QtKuaisuRumenXilieJiaocheng/font/fontello.eot
QtKuaisuRumenXilieJiaocheng/font/fontello.svg
QtKuaisuRumenXilieJiaocheng/font/fontello.ttf
QtKuaisuRumenXilieJiaocheng/font/fontello.woff
QtKuaisuRumenXilieJiaocheng/img/__init__.py
QtKuaisuRumenXilieJiaocheng/img/annotator-glyph-sprite.png
QtKuaisuRumenXilieJiaocheng/img/annotator-icon-sprite.png
QtKuaisuRumenXilieJiaocheng/img/apple-touch-icon.png
QtKuaisuRumenXilieJiaocheng/img/cancelfullscreen.png
QtKuaisuRumenXilieJiaocheng/img/close.png
QtKuaisuRumenXilieJiaocheng/img/fullscreen.png
QtKuaisuRumenXilieJiaocheng/img/loader.gif
QtKuaisuRumenXilieJiaocheng/img/menu-icon.png
QtKuaisuRumenXilieJiaocheng/img/save.png
QtKuaisuRumenXilieJiaocheng/img/saved.png
QtKuaisuRumenXilieJiaocheng/img/settings-s.png
QtKuaisuRumenXilieJiaocheng/img/settings.png
QtKuaisuRumenXilieJiaocheng/img/star.png
QtKuaisuRumenXilieJiaocheng/js/__init__.py
QtKuaisuRumenXilieJiaocheng/js/epub.js
QtKuaisuRumenXilieJiaocheng/js/epub.min.js
QtKuaisuRumenXilieJiaocheng/js/epub.min.map
QtKuaisuRumenXilieJiaocheng/js/hooks.min.js
QtKuaisuRumenXilieJiaocheng/js/hooks.min.map
QtKuaisuRumenXilieJiaocheng/js/reader.js
QtKuaisuRumenXilieJiaocheng/js/reader.js.map
QtKuaisuRumenXilieJiaocheng/js/reader.min.js
QtKuaisuRumenXilieJiaocheng/js/reader.min.map
QtKuaisuRumenXilieJiaocheng/js/hooks/__init__.py
QtKuaisuRumenXilieJiaocheng/js/hooks/extensions/__init__.py
QtKuaisuRumenXilieJiaocheng/js/hooks/extensions/highlight.js
QtKuaisuRumenXilieJiaocheng/js/libs/__init__.py
qt_kuaisu_rumen_xilie_jiaocheng-2024.3.1.0.dist-info/METADATA
qt_kuaisu_rumen_xilie_jiaocheng-2024.3.1.0.dist-info/WHEEL
qt_kuaisu_rumen_xilie_jiaocheng-2024.3.1.0.dist-info/entry_points.txt
qt_kuaisu_rumen_xilie_jiaocheng-2024.3.1.0.dist-info/top_level.txt
qt_kuaisu_rumen_xilie_jiaocheng-2024.3.1.0.dist-info/RECORD
